{
    "/admin/desktop/js/app.js": "/admin/desktop/js/app.js?id=70603dc5d1d3ed5de28f",
    "/admin/mobile/js/app.js": "/admin/mobile/js/app.js?id=bc8be2c39016c9160984",
    "/front/desktop/js/app.js": "/front/desktop/js/app.js?id=ddd2aa3f70fcc2f8a81c",
    "/front/mobile/js/app.js": "/front/mobile/js/app.js?id=6647f0401e1e10c06bb8",
    "/front/mobile/css/app.css": "/front/mobile/css/app.css?id=a3b9e1d29a590efb9ec7",
    "/front/desktop/css/app.css": "/front/desktop/css/app.css?id=87abbe5555f76887a1e3",
    "/admin/mobile/css/app.css": "/admin/mobile/css/app.css?id=9c9e0b2cf0f98cbff01c",
    "/admin/desktop/css/app.css": "/admin/desktop/css/app.css?id=4033c0d5763cc142fb86"
}
